abutils/__init__.py
abutils/bin.py
abutils/cl.py
abutils/io.py
abutils/log.py
abutils/pl.py
abutils/pp.py
abutils/tl.py
abutils/version.py
abutils/binaries/cdhit_darwin_amd64
abutils/binaries/cdhit_darwin_arm64
abutils/binaries/cdhit_linux_amd64
abutils/binaries/fastp_darwin
abutils/binaries/fastp_linux
abutils/binaries/fasttree_darwin_amd64
abutils/binaries/fasttree_darwin_arm64
abutils/binaries/fasttree_linux_amd64
abutils/binaries/minimap2_darwin_arm64
abutils/binaries/minimap2_linux_amd64
abutils/binaries/mmseqs_darwin_amd64
abutils/binaries/mmseqs_darwin_arm64
abutils/binaries/mmseqs_linux_amd64
abutils/binaries/muscle3_darwin
abutils/binaries/muscle3_linux
abutils/binaries/muscle_darwin_amd64
abutils/binaries/muscle_darwin_arm64
abutils/binaries/muscle_linux_amd64
abutils/binaries/sickle_darwin_arm64
abutils/binaries/sickle_linux_amd64
abutils/binaries/vsearch_darwin_amd64
abutils/binaries/vsearch_darwin_arm64
abutils/binaries/vsearch_linux_amd64
abutils/binaries/mafft_darwin/mafft.bat
abutils/binaries/mafft_darwin/mafftdir/bin/mafft
abutils/binaries/mafft_darwin/mafftdir/libexec/addsingle
abutils/binaries/mafft_darwin/mafftdir/libexec/contrafoldwrap
abutils/binaries/mafft_darwin/mafftdir/libexec/countlen
abutils/binaries/mafft_darwin/mafftdir/libexec/dash_client
abutils/binaries/mafft_darwin/mafftdir/libexec/disttbfast
abutils/binaries/mafft_darwin/mafftdir/libexec/dndblast
abutils/binaries/mafft_darwin/mafftdir/libexec/dndfast7
abutils/binaries/mafft_darwin/mafftdir/libexec/dndpre
abutils/binaries/mafft_darwin/mafftdir/libexec/dvtditr
abutils/binaries/mafft_darwin/mafftdir/libexec/f2cl
abutils/binaries/mafft_darwin/mafftdir/libexec/filter
abutils/binaries/mafft_darwin/mafftdir/libexec/getlag
abutils/binaries/mafft_darwin/mafftdir/libexec/hex2maffttext
abutils/binaries/mafft_darwin/mafftdir/libexec/mafft-distance
abutils/binaries/mafft_darwin/mafftdir/libexec/mafft-homologs.1
abutils/binaries/mafft_darwin/mafftdir/libexec/mafft-profile
abutils-0.5.3.dist-info/licenses/LICENSE
abutils-0.5.3.dist-info/METADATA
abutils-0.5.3.dist-info/WHEEL
abutils-0.5.3.dist-info/top_level.txt
abutils-0.5.3.dist-info/RECORD
