Metadata-Version: 2.4
Name: abutils
Version: 0.5.3
Summary: Utilities for analysis of adaptive immune receptor repertoire (AIRR) data
Home-page: https://github.com/briney/abutils
Author: Bryan Briney
Author-email: briney@scripps.edu
Classifier: Development Status :: 5 - Production/Stable
Classifier: Intended Audience :: Science/Research
Classifier: License :: OSI Approved :: MIT License
Classifier: Operating System :: OS Independent
Classifier: Programming Language :: Python :: 3
Classifier: Programming Language :: Python :: 3.10
Classifier: Programming Language :: Python :: 3.11
Classifier: Programming Language :: Python :: 3.12
Classifier: Programming Language :: Python :: 3.13
Classifier: Topic :: Scientific/Engineering :: Bio-Informatics
Requires-Python: >=3.10
License-File: LICENSE
Requires-Dist: abstar>=0.7
Requires-Dist: baltic
Requires-Dist: biopython>=1.78
Requires-Dist: dnachisel
Requires-Dist: fastcluster
Requires-Dist: matplotlib
Requires-Dist: mnemonic
Requires-Dist: natsort
Requires-Dist: numpy<2
Requires-Dist: pandas
Requires-Dist: paramiko
Requires-Dist: parasail
Requires-Dist: polars>=1.6
Requires-Dist: prettytable
Requires-Dist: pyarrow
Requires-Dist: pyfamsa
Requires-Dist: pyfastx
Requires-Dist: pytest
Requires-Dist: python-circos
Requires-Dist: pyyaml
Requires-Dist: rapidfuzz
Requires-Dist: sample-sheet
Requires-Dist: scikit-learn
Requires-Dist: scipy
Requires-Dist: seaborn>=0.11
Requires-Dist: smart_open
Requires-Dist: tqdm
Dynamic: author
Dynamic: author-email
Dynamic: classifier
Dynamic: description
Dynamic: description-content-type
Dynamic: home-page
Dynamic: license-file
Dynamic: requires-dist
Dynamic: requires-python
Dynamic: summary
